tucker_conv/__init__.py
tucker_conv/conv.py
tucker_conv/tucker_conv.py
tucker_conv-1.0.1.dist-info/LICENSE
tucker_conv-1.0.1.dist-info/METADATA
tucker_conv-1.0.1.dist-info/WHEEL
tucker_conv-1.0.1.dist-info/top_level.txt
tucker_conv-1.0.1.dist-info/RECORD
