Metadata-Version: 2.1
Name: tucker-conv
Version: 1.0.1
Summary: Implementation of Tucker Convolution Layer
Home-page: https://github.com/novice03/tucker-conv
Author: Pranav Pulijala
License: UNKNOWN
Platform: UNKNOWN
Classifier: Programming Language :: Python :: 3
Classifier: Operating System :: OS Independent
